stackless.py
stacklessemu-0.1.dist-info/DESCRIPTION.rst
stacklessemu-0.1.dist-info/METADATA
stacklessemu-0.1.dist-info/metadata.json
stacklessemu-0.1.dist-info/RECORD
stacklessemu-0.1.dist-info/top_level.txt
stacklessemu-0.1.dist-info/WHEEL
