Metadata-Version: 2.0
Name: stacklessemu
Version: 0.1
Summary: A quick lightweight psuedo-installation of a subset of Stackless Python functionality.
Home-page: https://bitbucket.org/rmtew/greenstackless
Author: Richard Tew
Author-email: richard.m.tew@gmail.com
License: UNKNOWN
Platform: UNKNOWN
Classifier: License :: OSI Approved :: BSD License
Classifier: Programming Language :: Python :: 2.5
Classifier: Programming Language :: Python :: 2.6
Classifier: Programming Language :: Python :: 2.7
Classifier: Operating System :: MacOS :: MacOS X
Classifier: Operating System :: POSIX
Classifier: Operating System :: Microsoft :: Windows
Classifier: Topic :: Software Development :: Libraries :: Python Modules
Classifier: Intended Audience :: Developers
Classifier: Development Status :: 4 - Beta
Requires-Dist: greenlet
